py_crypto_hd_wallet/__init__.py
py_crypto_hd_wallet/_version.py
py_crypto_hd_wallet/algorand/__init__.py
py_crypto_hd_wallet/algorand/hd_wallet_algorand.py
py_crypto_hd_wallet/algorand/hd_wallet_algorand_enum.py
py_crypto_hd_wallet/algorand/hd_wallet_algorand_factory.py
py_crypto_hd_wallet/algorand/hd_wallet_algorand_keys.py
py_crypto_hd_wallet/bip/__init__.py
py_crypto_hd_wallet/bip/hd_wallet_bip.py
py_crypto_hd_wallet/bip/hd_wallet_bip_addr.py
py_crypto_hd_wallet/bip/hd_wallet_bip_enum.py
py_crypto_hd_wallet/bip/hd_wallet_bip_factory.py
py_crypto_hd_wallet/bip/hd_wallet_bip_keys.py
py_crypto_hd_wallet/cardano/__init__.py
py_crypto_hd_wallet/cardano/shelley/__init__.py
py_crypto_hd_wallet/cardano/shelley/hd_wallet_cardano_shelley.py
py_crypto_hd_wallet/cardano/shelley/hd_wallet_cardano_shelley_addr.py
py_crypto_hd_wallet/cardano/shelley/hd_wallet_cardano_shelley_enum.py
py_crypto_hd_wallet/cardano/shelley/hd_wallet_cardano_shelley_factory.py
py_crypto_hd_wallet/cardano/shelley/hd_wallet_cardano_shelley_keys.py
py_crypto_hd_wallet/common/__init__.py
py_crypto_hd_wallet/common/hd_wallet_addr_base.py
py_crypto_hd_wallet/common/hd_wallet_base.py
py_crypto_hd_wallet/common/hd_wallet_data_types.py
py_crypto_hd_wallet/common/hd_wallet_enum_dict.py
py_crypto_hd_wallet/common/hd_wallet_keys_base.py
py_crypto_hd_wallet/electrum/__init__.py
py_crypto_hd_wallet/electrum/v1/__init__.py
py_crypto_hd_wallet/electrum/v1/hd_wallet_electrum_v1.py
py_crypto_hd_wallet/electrum/v1/hd_wallet_electrum_v1_addr.py
py_crypto_hd_wallet/electrum/v1/hd_wallet_electrum_v1_enum.py
py_crypto_hd_wallet/electrum/v1/hd_wallet_electrum_v1_factory.py
py_crypto_hd_wallet/electrum/v1/hd_wallet_electrum_v1_keys.py
py_crypto_hd_wallet/electrum/v2/__init__.py
py_crypto_hd_wallet/electrum/v2/hd_wallet_electrum_v2.py
py_crypto_hd_wallet/electrum/v2/hd_wallet_electrum_v2_addr.py
py_crypto_hd_wallet/electrum/v2/hd_wallet_electrum_v2_enum.py
py_crypto_hd_wallet/electrum/v2/hd_wallet_electrum_v2_factory.py
py_crypto_hd_wallet-1.3.3.dist-info/LICENSE
py_crypto_hd_wallet-1.3.3.dist-info/METADATA
py_crypto_hd_wallet-1.3.3.dist-info/WHEEL
py_crypto_hd_wallet-1.3.3.dist-info/top_level.txt
py_crypto_hd_wallet-1.3.3.dist-info/RECORD
