Metadata-Version: 2.1
Name: py_crypto_hd_wallet
Version: 1.3.3
Summary: HD (Hierarchical Deterministic) wallet for cryptocurrencies based on bip_utils library
Home-page: https://github.com/ebellocchia/py_crypto_hd_wallet
Download-URL: https://github.com/ebellocchia/py_crypto_hd_wallet/archive/v1.3.3.tar.gz
Author: Emanuele Bellocchia
Author-email: ebellocchia@gmail.com
Maintainer: Emanuele Bellocchia
Maintainer-email: ebellocchia@gmail.com
License: MIT
Keywords: python,cryptography,ecdsa,ed25519,ed25519-blake2b,nist256p1,secp256k1,sr25519,wallet,hd-wallet,slip10,slip0010,bip39,bip39-substrate,bip32,bip44,bip49,bip84,bech32,bech32m,segwit,electrum,substrate,taproot,daedalus,byron,shelley,akash,algorand,atom,avalanche,avax,band protocol,binance chain,binance smart chain,bitcoin,bitcoin cash,bitcoinsv,bnb,cardano,cardano-byron,cardano-shelley,celo,certik,cosmos,dash,dogecoin,ecash,elrond,eos,ethereum,ethereum classic,fantom opera,filecoin,harmony
Platform: any
Classifier: Programming Language :: Python :: 3.7
Classifier: Programming Language :: Python :: 3.8
Classifier: Programming Language :: Python :: 3.9
Classifier: Programming Language :: Python :: 3.10
Classifier: Programming Language :: Python :: 3.11
Classifier: Programming Language :: Python :: 3.12
Classifier: Development Status :: 5 - Production/Stable
Classifier: License :: OSI Approved :: MIT License
Classifier: Operating System :: OS Independent
Classifier: Intended Audience :: Developers
Requires-Python: >=3.7
License-File: LICENSE
Requires-Dist: bip-utils <3.0.0,>=2.9.0 ; python_version < "3.12"
Requires-Dist: bip-utils <3.0.0,>=2.9.2 ; python_version >= "3.12"
Provides-Extra: develop
Requires-Dist: coverage >=5.3 ; extra == 'develop'
Requires-Dist: flake8 >=3.8 ; extra == 'develop'
Requires-Dist: isort >=5.8 ; extra == 'develop'
Requires-Dist: mypy >=0.900 ; extra == 'develop'
Requires-Dist: prospector[with_mypy,with_pyroma] >=1.7 ; extra == 'develop'
Requires-Dist: pytest >=7.0 ; extra == 'develop'
Requires-Dist: pytest-cov >=2.10 ; extra == 'develop'
